DEV-NOTES
LICENSE.txt
MANIFEST.in
README.rst
setup.py
doc/Makefile
doc/changes.rst
doc/cmdline.rst
doc/conf.py
doc/conventions.rst
doc/datasets.rst
doc/format.rst
doc/index.rst
doc/library.rst
doc/logistics.rst
doc/make.bat
doc/requirements.txt
doc/example/tiny-4grams.txt
doc/example/tiny-4grams.zs
doc/figures/README
doc/figures/format-details.svg
doc/figures/format-overview.svg
zs/__init__.py
zs/__main__.py
zs/_zs.c
zs/common.py
zs/futures.py
zs/pycrc-crc64xz.c
zs/pycrc-crc64xz.h
zs/reader.py
zs/transport.py
zs/version.py
zs/writer.py
zs.egg-info/PKG-INFO
zs.egg-info/SOURCES.txt
zs.egg-info/dependency_links.txt
zs.egg-info/entry_points.txt
zs.egg-info/requires.txt
zs.egg-info/top_level.txt
zs/cmdline/__init__.py
zs/cmdline/dump.py
zs/cmdline/info.py
zs/cmdline/main.py
zs/cmdline/make.py
zs/cmdline/util.py
zs/cmdline/validate.py
zs/tests/__init__.py
zs/tests/http_harness.py
zs/tests/test__zs.py
zs/tests/test_cmdline.py
zs/tests/test_common.py
zs/tests/test_futures.py
zs/tests/test_reader.py
zs/tests/test_transport.py
zs/tests/test_writer.py
zs/tests/util.py
zs/tests/data/letters-deflate.zs
zs/tests/data/letters-lzma.zs
zs/tests/data/letters-none.zs
zs/tests/data/make-letters.py
zs/tests/data/broken-files/bad-codec.zs
zs/tests/data/broken-files/bad-data-order.zs
zs/tests/data/broken-files/bad-index-key-1.zs
zs/tests/data/broken-files/bad-index-key-2.zs
zs/tests/data/broken-files/bad-index-key-3.zs
zs/tests/data/broken-files/bad-index-order.zs
zs/tests/data/broken-files/bad-level-index-1.zs
zs/tests/data/broken-files/bad-level-index-2.zs
zs/tests/data/broken-files/bad-level-root.zs
zs/tests/data/broken-files/bad-magic.zs
zs/tests/data/broken-files/bad-ref-length.zs
zs/tests/data/broken-files/bad-sha256.zs
zs/tests/data/broken-files/bad-total-length.zs
zs/tests/data/broken-files/empty-data.zs
zs/tests/data/broken-files/empty-index.zs
zs/tests/data/broken-files/good-extension-blocks.zs
zs/tests/data/broken-files/good-extension-header-fields.zs
zs/tests/data/broken-files/good-index-key-1.zs
zs/tests/data/broken-files/good-index-key-2.zs
zs/tests/data/broken-files/good-index-key-3.zs
