Metadata-Version: 1.1
Name: zs
Version: 0.10.0
Summary: ZS is a compressed, read-only file format for efficiently distributing, querying, and archiving arbitrarily large record-oriented datasets.
Home-page: https://github.com/njsmith/zs
Author: Nathaniel J. Smith
Author-email: njs@pobox.com
License: 2-clause BSD
Platform: UNKNOWN
Classifier: Development Status :: 4 - Beta
Classifier: Intended Audience :: Developers
Classifier: Intended Audience :: Science/Research
Classifier: License :: OSI Approved :: BSD License
Classifier: Programming Language :: Python :: 2
Classifier: Programming Language :: Python :: 3
